functions_core_lib/__init__.py
functions_core_lib/generate_knowledge_base.py
functions_core_lib/functions/__init__.py
functions_core_lib/functions/stripe_create_customer.py
functions_core_lib/functions/stripe_delete_customer.py
functions_core_lib/stripe/exceptions.py
functions_core_lib/stripe/logger.py
functions_core_lib/stripe/stripe_client.py
functions_core_lib/stripe/types.py
mainttracker_functions_core_lib-0.2.0.dist-info/METADATA
mainttracker_functions_core_lib-0.2.0.dist-info/WHEEL
mainttracker_functions_core_lib-0.2.0.dist-info/top_level.txt
mainttracker_functions_core_lib-0.2.0.dist-info/RECORD
